cv2pencil/LICENSE
cv2pencil/README.MD
cv2pencil/__init__.py
cv2pencil/requirements.txt
cv2pencil/thirdparty.json
cv2pencil-0.10.dist-info/LICENSE.rst
cv2pencil-0.10.dist-info/METADATA
cv2pencil-0.10.dist-info/WHEEL
cv2pencil-0.10.dist-info/top_level.txt
cv2pencil-0.10.dist-info/RECORD
